Workbook
Name aporte: APP!$D$19
Name patrimonio: APP!$D$22
Name qtd_anos: APP!$D$20
Name rendimento_carteira: APP!$D$15
Name salario: APP!$D$14
Name sugestao_investimento: APP!$D$16
Name taxa_mensal: APP!$D$21

Sheet APP
B13: CONFIGURAÇÕES
B14: Salário | D14: 2000
B15: Rendimento Carteira | D15: 0.006
B16: Sugestão de Investimento | D16: =D14*30% -> 600
B18: INVESTIMENTO MENSAL
B19: Quanto investir por mês? | D19: 200
B20: Por quantos anos? | D20: 5
B21: Taxa de Rendimento mensal? | D21: 0.01079
B22: Patrimônio acumulado? | D22: =FV(taxa_mensal,qtd_anos*12,aporte*-1) -> 16755.383
B23: Dividendos Mensais? | D23: =patrimonio*rendimento_carteira -> 100.5323
B25: CENÁRIOS | D25: Dividendo
A26: 2 | B26: Quanto em 2 Anos? | C26: =FV($D$21,$A26*12,$D$19*-1) -> 5445.5255 | D26: =C26*rendimento_carteira -> 32.673153
A27: 5 | B27: Quanto em 5 Anos? | C27: =FV($D$21,$A27*12,$D$19*-1) -> 16755.383 | D27: =C27*rendimento_carteira -> 100.5323
A28: 10 | B28: Quanto em 10 Anos? | C28: =FV($D$21,$A28*12,$D$19*-1) -> 48656.843 | D28: =C28*rendimento_carteira -> 291.94106
A29: 20 | B29: Quanto em 20 Anos? | C29: =FV($D$21,$A29*12,$D$19*-1) -> 225039.68 | D29: =C29*rendimento_carteira -> 1350.2381
A30: 30 | B30: Quanto em 30 Anos? | C30: =FV($D$21,$A30*12,$D$19*-1) -> 864433.93 | D30: =C30*rendimento_carteira -> 5186.6036
B33: PERFIL | D33: Moderado
B34: VALOR A SER INVESTIDO POR MÊS | D34: =aporte -> 200
B36: TIPO DE FII | C36: Percentual Sugerido | D36: Valores
B37: PAPEL | C37: =VLOOKUP($D$33&"-"&B37,'Tabela de Apoio'!$A:$D,4,FALSE) -> 0.32 | D37: =C37*$D$34 -> 64
B38: TIJOLO | C38: =VLOOKUP($D$33&"-"&B38,'Tabela de Apoio'!$A:$D,4,FALSE) -> 0.35 | D38: =C38*$D$34 -> 70
B39: HÍBRIDOS | C39: =VLOOKUP($D$33&"-"&B39,'Tabela de Apoio'!$A:$D,4,FALSE) -> 0.08 | D39: =C39*$D$34 -> 16
B40: FOFS | C40: =VLOOKUP($D$33&"-"&B40,'Tabela de Apoio'!$A:$D,4,FALSE) -> 0.05 | D40: =C40*$D$34 -> 10
B41: DESENVOLVIMENTO | C41: =VLOOKUP($D$33&"-"&B41,'Tabela de Apoio'!$A:$D,4,FALSE) -> 0.1 | D41: =C41*$D$34 -> 20
B42: HOTELARIAS | C42: =VLOOKUP($D$33&"-"&B42,'Tabela de Apoio'!$A:$D,4,FALSE) -> 0.1 | D42: =C42*$D$34 -> 20
D43: =SUM(D37:D42) -> 200

Sheet Tabela de Apoio
A2: CHAVE | B2: PERFIL | C2: TIPO DE FII | D2: PERCENTUAL
A3: =B3&"-"&C3 -> Conservador-PAPEL | B3: Conservador | C3: PAPEL | D3: 0.3 | F3: =A10 -> Moderado-TIJOLO | G3: =VLOOKUP(F3,$A:$D,4,FALSE) -> 0.35
A4: =B4&"-"&C4 -> Conservador-TIJOLO | B4: Conservador | C4: TIJOLO | D4: 0.5
A5: =B5&"-"&C5 -> Conservador-HÍBRIDOS | B5: Conservador | C5: HÍBRIDOS | D5: 0.1
A6: =B6&"-"&C6 -> Conservador-FOFS | B6: Conservador | C6: FOFS | D6: 0.1
A7: =B7&"-"&C7 -> Conservador-DESENVOLVIMENTO | B7: Conservador | C7: DESENVOLVIMENTO | D7: 0
A8: =B8&"-"&C8 -> Conservador-HOTELARIAS | B8: Conservador | C8: HOTELARIAS | D8: 0
A9: =B9&"-"&C9 -> Moderado-PAPEL | B9: Moderado | C9: PAPEL | D9: 0.32
A10: =B10&"-"&C10 -> Moderado-TIJOLO | B10: Moderado | C10: TIJOLO | D10: 0.35
A11: =B11&"-"&C11 -> Moderado-HÍBRIDOS | B11: Moderado | C11: HÍBRIDOS | D11: 0.08
A12: =B12&"-"&C12 -> Moderado-FOFS | B12: Moderado | C12: FOFS | D12: 0.05
A13: =B13&"-"&C13 -> Moderado-DESENVOLVIMENTO | B13: Moderado | C13: DESENVOLVIMENTO | D13: 0.1
A14: =B14&"-"&C14 -> Moderado-HOTELARIAS | B14: Moderado | C14: HOTELARIAS | D14: 0.1
A15: =B15&"-"&C15 -> Agressivo-PAPEL | B15: Agressivo | C15: PAPEL | D15: 0.5
... A20: =B20&"-"&C20 -> Agressivo-HOTELARIAS | B20: Agressivo | C20: HOTELARIAS | D20: 0.1
